README
almost.py
setup.py
almost.egg-info/PKG-INFO
almost.egg-info/SOURCES.txt
almost.egg-info/dependency_links.txt
almost.egg-info/requires.txt
almost.egg-info/top_level.txt